pn5180_tagomatic/__init__.py
pn5180_tagomatic/constants.py
pn5180_tagomatic/iso14443a.py
pn5180_tagomatic/iso15693.py
pn5180_tagomatic/pn5180.py
pn5180_tagomatic/proxy.py
pn5180_tagomatic/py.typed
pn5180_tagomatic/session.py
pn5180_tagomatic-0.0.3.dist-info/licenses/LICENSE
pn5180_tagomatic-0.0.3.dist-info/METADATA
pn5180_tagomatic-0.0.3.dist-info/WHEEL
pn5180_tagomatic-0.0.3.dist-info/top_level.txt
pn5180_tagomatic-0.0.3.dist-info/RECORD
