Metadata-Version: 2.4
Name: pn5180-tagomatic
Version: 0.0.3
Summary: USB based RFID reader with Python interface
Author: PN5180-tagomatic contributors
License: GPL-3.0-or-later
Project-URL: Homepage, https://github.com/bofh69/PN5180-tagomatic
Project-URL: Repository, https://github.com/bofh69/PN5180-tagomatic
Project-URL: Issues, https://github.com/bofh69/PN5180-tagomatic/issues
Keywords: rfid,pn5180,usb,reader,raspberry-pi-pico
Classifier: Development Status :: 3 - Alpha
Classifier: Intended Audience :: Developers
Classifier: Programming Language :: Python :: 3
Classifier: Programming Language :: Python :: 3.10
Classifier: Programming Language :: Python :: 3.11
Classifier: Programming Language :: Python :: 3.12
Classifier: Programming Language :: Python :: 3.13
Classifier: Programming Language :: Python :: 3.14
Classifier: Topic :: Software Development :: Libraries :: Python Modules
Classifier: Topic :: System :: Hardware
Requires-Python: >=3.10
License-File: LICENSE
Requires-Dist: pyserial>=3.5
Requires-Dist: arduino-simple-rpc>=2.4.0
Requires-Dist: setuptools>=65.0.0
Provides-Extra: dev
Requires-Dist: pytest>=7.0.0; extra == "dev"
Requires-Dist: pytest-cov>=4.0.0; extra == "dev"
Requires-Dist: ruff>=0.1.0; extra == "dev"
Requires-Dist: mypy>=1.0.0; extra == "dev"
Requires-Dist: black>=23.0.0; extra == "dev"
Requires-Dist: types-pyserial>=3.5.0; extra == "dev"
Dynamic: license-file
